{
  "symbol": "SHFE.ag",
  "volatility_3m": 0.8816259684506957,
  "volatility_1y": 0.5154457026490245,
  "volatility_5y": 0.2834267334960923,
  "volatility_weighted": "High",
  "trend_strength_3m": 18.12,
  "trend_strength_1y": 18.12,
  "trend_strength_weighted": "Weak",
  "autocorr_3m": 0.063439909713564,
  "autocorr_1y": 0.046208838642799274,
  "skewness": -1.0160369781952743,
  "kurtosis": 95.47215270603371,
  "liquidity": "Low",
  "metadata": {
    "data_source": "Mini API (http://192.168.31.74:8105)",
    "calculation_time": "2026-04-25 23:54:08",
    "data_start_date": "2018-04-27T01:00:00",
    "data_end_date": "2026-04-22T05:30:00",
    "data_points_3m": 2001,
    "data_points_1y": 8721,
    "data_points_5y": 69128,
    "missing_data_ratio": 0.0
  },
  "confidence": {
    "overall": 0.9147502216618126,
    "volatility": 0.7868755541545316,
    "trend": 1.0,
    "liquidity": 1.0,
    "data_sufficiency": 1.0,
    "data_quality": 1.0,
    "feature_stability": 0.6447925902575528,
    "warnings": []
  }
}